amncore/__init__.py
amncore/compat.py
amncore/constants.py
amncore/fileutils.py
amncore/logger.py
amncore/mixins.py
amncore/ring_buff.py
amncore/sync.py
amncore/tasks.py
amncore/xcepts.py
amncore-0.2.13.dist-info/LICENSE
amncore-0.2.13.dist-info/METADATA
amncore-0.2.13.dist-info/WHEEL
amncore-0.2.13.dist-info/top_level.txt
amncore-0.2.13.dist-info/RECORD
