Metadata-Version: 2.1
Name: amncore
Version: 0.2.13
Summary: AmmuNation Framework core modules
Home-page: https://github.com/munshigroup/amncore
Author: The Munshi Group
Author-email: support@munshigroup.com
License: UNKNOWN
Platform: UNKNOWN
Classifier: Programming Language :: Python :: 3
Classifier: Programming Language :: Python :: 2.7
Classifier: License :: OSI Approved :: MIT License
Classifier: Operating System :: OS Independent
Requires-Dist: bombfuse
Requires-Dist: kthread
